scout/__init__.py
scout/adapter/__init__.py
scout/adapter/client.py
scout/adapter/mongo/__init__.py
scout/adapter/mongo/acmg.py
scout/adapter/mongo/base.py
scout/adapter/mongo/case.py
scout/adapter/mongo/case_events.py
scout/adapter/mongo/case_group.py
scout/adapter/mongo/ccv.py
scout/adapter/mongo/clinvar.py
scout/adapter/mongo/cytoband.py
scout/adapter/mongo/disease_terms.py
scout/adapter/mongo/event.py
scout/adapter/mongo/filter.py
scout/adapter/mongo/hgnc.py
scout/adapter/mongo/hpo.py
scout/adapter/mongo/index.py
scout/adapter/mongo/institute.py
scout/adapter/mongo/managed_variant.py
scout/adapter/mongo/matchmaker.py
scout/adapter/mongo/omics_variant.py
scout/adapter/mongo/panel.py
scout/adapter/mongo/phenomodel.py
scout/adapter/mongo/query.py
scout/adapter/mongo/rank_model.py
scout/adapter/mongo/transcript.py
scout/adapter/mongo/user.py
scout/adapter/mongo/variant.py
scout/adapter/mongo/variant_events.py
scout/adapter/mongo/variant_loader.py
scout/build/__init__.py
scout/build/acmg.py
scout/build/case.py
scout/build/ccv.py
scout/build/disease.py
scout/build/hpo.py
scout/build/individual.py
scout/build/institute.py
scout/build/managed_variant.py
scout/build/panel.py
scout/build/user.py
scout/build/genes/__init__.py
scout/build/genes/exon.py
scout/build/genes/hgnc_gene.py
scout/build/genes/transcript.py
scout/build/variant/__init__.py
scout/build/variant/clnsig.py
scout/build/variant/compound.py
scout/build/variant/gene.py
scout/build/variant/genotype.py
scout/build/variant/transcript.py
scout/build/variant/variant.py
scout/commands/__init__.py
scout/commands/base.py
scout/commands/convert.py
scout/commands/index_command.py
scout/commands/serve.py
scout/commands/utils.py
scout/commands/wipe_database.py
scout/commands/delete/__init__.py
scout/commands/delete/delete_command.py
scout/commands/download/__init__.py
scout/commands/download/download_command.py
scout/commands/download/ensembl.py
scout/commands/download/everything.py
scout/commands/download/exac.py
scout_browser-4.106.0.dist-info/METADATA
scout_browser-4.106.0.dist-info/WHEEL
scout_browser-4.106.0.dist-info/entry_points.txt
scout_browser-4.106.0.dist-info/licenses/LICENSE
scout_browser-4.106.0.dist-info/RECORD
