Metadata-Version: 2.4
Name: scout-browser
Version: 4.106.0
Summary: Clinical DNA variant visualizer and browser
Project-URL: Repository, https://github.com/Clinical-Genomics/scout
Project-URL: Changelog, https://github.com/Clinical-Genomics/scout/blob/main/CHANGELOG.md
Project-URL: Documentation, https://clinical-genomics.github.io/scout/
Project-URL: Bug Tracker, https://github.com/Clinical-Genomics/scout/issues
Project-URL: Issues, https://github.com/Clinical-Genomics/scout/issues
Author-email: Chiara Rasi <chiara.rasi@scilifelab.se>, Daniel Nilsson <daniel.nilsson@ki.se>, Robin Andeer <robin.andeer@gmail.com>, Mans Magnuson <monsunas@gmail.com>
License: MIT License
License-File: LICENSE
Keywords: acmg,beacon,cancer,clingen-cgc-vicc,clinvar,cnv,coverage,dna,fusion,genome visualisation,lrs,matchmaker exchange,ogm,outliers,panel,panelapp,phenopacket,rna,sma,snv,str,sv,variant ranking,variant triage,variants,vcf,wes,wgs,wts
Classifier: Development Status :: 5 - Production/Stable
Classifier: Environment :: Web Environment
Classifier: Intended Audience :: Developers
Classifier: Intended Audience :: Science/Research
Classifier: License :: OSI Approved :: MIT License
Classifier: Operating System :: MacOS :: MacOS X
Classifier: Operating System :: Unix
Classifier: Programming Language :: Python
Classifier: Programming Language :: Python :: 3.10
Classifier: Programming Language :: Python :: 3.11
Classifier: Programming Language :: Python :: 3.12
Classifier: Programming Language :: Python :: 3.13
Classifier: Programming Language :: Python :: 3.14
Classifier: Programming Language :: Python :: Implementation :: CPython
Classifier: Topic :: Internet :: WWW/HTTP :: Dynamic Content
Classifier: Topic :: Scientific/Engineering :: Bio-Informatics
Classifier: Topic :: Scientific/Engineering :: Medical Science Apps.
Requires-Python: >=3.10
Requires-Dist: anytree
Requires-Dist: authlib
Requires-Dist: chanjo-report>=4.12.0
Requires-Dist: click
Requires-Dist: coloredlogs
Requires-Dist: configobj
Requires-Dist: cryptography
Requires-Dist: cyvcf2
Requires-Dist: defusedxml
Requires-Dist: flask-babel>=3
Requires-Dist: flask-bootstrap
Requires-Dist: flask-cors
Requires-Dist: flask-ldap3-login>=1.0.2
Requires-Dist: flask-login
Requires-Dist: flask-mail
Requires-Dist: flask-wtf
Requires-Dist: flask>=2.0
Requires-Dist: importlib-resources
Requires-Dist: intervaltree==3.0.2
Requires-Dist: livereload>=2.7
Requires-Dist: markdown
Requires-Dist: path-py
Requires-Dist: pathlib
Requires-Dist: pdfkit
Requires-Dist: ped-parser
Requires-Dist: phenopackets
Requires-Dist: pydantic>=2
Requires-Dist: pymongo
Requires-Dist: python-dateutil
Requires-Dist: pyyaml>=5.1
Requires-Dist: query-phenomizer
Requires-Dist: tabulate
Requires-Dist: tornado>=6.4.1
Requires-Dist: werkzeug
Requires-Dist: wtforms
Requires-Dist: xlsxwriter
Provides-Extra: coverage
Requires-Dist: chanjo-report; extra == 'coverage'
Requires-Dist: pymysql; extra == 'coverage'
Requires-Dist: python-dateutil; extra == 'coverage'
